Plasmidsimilarity/Snakefile
Plasmidsimilarity/__init__.py
Plasmidsimilarity/cli.py
Plasmidsimilarity/logo.txt
Plasmidsimilarity/scripts/__init__.py
Plasmidsimilarity/scripts/abricate_summary.py
Plasmidsimilarity/scripts/combinedplot.py
Plasmidsimilarity/scripts/describe.py
Plasmidsimilarity/scripts/graphextract.py
Plasmidsimilarity/scripts/heatmap.py
Plasmidsimilarity/scripts/plasmidmerge.py
Plasmidsimilarity/scripts/plasmidplots.py
Plasmidsimilarity/scripts/plasmidread.py
Plasmidsimilarity/scripts/unique.py
Plasmidsimilarity/testdata/MG800340.1.fasta
Plasmidsimilarity/testdata/MH061380.1.fasta
Plasmidsimilarity/testdata/MK360916.1.fasta
Plasmidsimilarity/testdata/NZ_CP038265.1.fasta
Plasmidsimilarity/testdata/NZ_CP040891.1.fasta
Plasmidsimilarity-1.0.1.dist-info/AUTHORS.rst
Plasmidsimilarity-1.0.1.dist-info/LICENSE
Plasmidsimilarity-1.0.1.dist-info/METADATA
Plasmidsimilarity-1.0.1.dist-info/WHEEL
Plasmidsimilarity-1.0.1.dist-info/entry_points.txt
Plasmidsimilarity-1.0.1.dist-info/top_level.txt
Plasmidsimilarity-1.0.1.dist-info/RECORD
