Metadata-Version: 2.1
Name: Plasmidsimilarity
Version: 1.0.1
Summary: Comparing plasmid sequences and its gene content
Home-page: https://github.com/casperjamin/Plasmidsimilarity
Author: Casper Jamin
Author-email: casperjamin@gmail.com
License: BSD license
Keywords: Plasmidsimilarity
Platform: UNKNOWN
Classifier: Development Status :: 2 - Pre-Alpha
Classifier: Intended Audience :: Developers
Classifier: License :: OSI Approved :: BSD License
Classifier: Natural Language :: English
Classifier: Programming Language :: Python :: 3
Classifier: Programming Language :: Python :: 3.6
Classifier: Programming Language :: Python :: 3.7
Classifier: Programming Language :: Python :: 3.8
Requires-Python: >3.5
Requires-Dist: tables
Requires-Dist: pyyaml
Requires-Dist: pandas
Requires-Dist: joblib
Requires-Dist: networkx
Requires-Dist: scipy
Requires-Dist: snakemake (<6)
Requires-Dist: matplotlib
Requires-Dist: seaborn
Requires-Dist: biopython
